setup.py
lzytools_Qt/__init__.py
lzytools_Qt/_button.py
lzytools_Qt/_dialog.py
lzytools_Qt/_label.py
lzytools_Qt/_lineEdit.py
lzytools_Qt/_mainWindow.py
lzytools_Qt/_slider.py
lzytools_Qt/_styledItemDelegate.py
lzytools_Qt/_tableWidget.py
lzytools_Qt/_timer.py
lzytools_Qt/_utils.py
lzytools_Qt.egg-info/PKG-INFO
lzytools_Qt.egg-info/SOURCES.txt
lzytools_Qt.egg-info/dependency_links.txt
lzytools_Qt.egg-info/top_level.txt