Metadata-Version: 2.4
Name: lzytools_Qt
Version: 0.0.3
Summary: Python自用包-Qt相关方法
Home-page: https://github.com/PPJUST/lzytools
Author: PPJUST
Requires-Python: >=3
Dynamic: author
Dynamic: description
Dynamic: description-content-type
Dynamic: home-page
Dynamic: requires-python
Dynamic: summary
